<annotation>
	<folder>JPEGImages</folder>
	<filename>4 (222).jpg</filename>
	<path>C:\Users\赵文龙\Desktop\VOC2007\JPEGImages\4 (222).jpg</path>
	<source>
		<database>Unknown</database>
	</source>
	<size>
		<width>256</width>
		<height>449</height>
		<depth>3</depth>
	</size>
	<segmented>0</segmented>
	<object>
		<name>Corn rust leaf</name>
		<pose>Unspecified</pose>
		<truncated>0</truncated>
		<difficult>0</difficult>
		<bndbox>
			<xmin>26</xmin>
			<ymin>14</ymin>
			<xmax>240</xmax>
			<ymax>337</ymax>
		</bndbox>
	</object>
</annotation>
