<annotation>
	<folder>JPEGImages</folder>
	<filename>2 (314).jpg</filename>
	<path>C:\Users\赵文龙\Desktop\VOC2007\JPEGImages\2 (314).jpg</path>
	<source>
		<database>Unknown</database>
	</source>
	<size>
		<width>2880</width>
		<height>2160</height>
		<depth>3</depth>
	</size>
	<segmented>0</segmented>
	<object>
		<name>Powdery Mildew</name>
		<pose>Unspecified</pose>
		<truncated>0</truncated>
		<difficult>0</difficult>
		<bndbox>
			<xmin>971</xmin>
			<ymin>354</ymin>
			<xmax>1588</xmax>
			<ymax>1998</ymax>
		</bndbox>
	</object>
	<object>
		<name>Powdery Mildew</name>
		<pose>Unspecified</pose>
		<truncated>1</truncated>
		<difficult>0</difficult>
		<bndbox>
			<xmin>2076</xmin>
			<ymin>794</ymin>
			<xmax>2880</xmax>
			<ymax>2012</ymax>
		</bndbox>
	</object>
</annotation>
