<annotation>
	<folder>JPEGImages</folder>
	<filename>2 (47).jpg</filename>
	<path>C:\Users\赵文龙\Desktop\VOC2007\JPEGImages\2 (47).jpg</path>
	<source>
		<database>Unknown</database>
	</source>
	<size>
		<width>2000</width>
		<height>1098</height>
		<depth>3</depth>
	</size>
	<segmented>0</segmented>
	<object>
		<name>Leaf Rust</name>
		<pose>Unspecified</pose>
		<truncated>1</truncated>
		<difficult>0</difficult>
		<bndbox>
			<xmin>1</xmin>
			<ymin>460</ymin>
			<xmax>391</xmax>
			<ymax>1098</ymax>
		</bndbox>
	</object>
	<object>
		<name>Leaf Rust</name>
		<pose>Unspecified</pose>
		<truncated>0</truncated>
		<difficult>0</difficult>
		<bndbox>
			<xmin>765</xmin>
			<ymin>14</ymin>
			<xmax>1217</xmax>
			<ymax>1011</ymax>
		</bndbox>
	</object>
	<object>
		<name>Leaf Rust</name>
		<pose>Unspecified</pose>
		<truncated>1</truncated>
		<difficult>0</difficult>
		<bndbox>
			<xmin>1457</xmin>
			<ymin>176</ymin>
			<xmax>2000</xmax>
			<ymax>1088</ymax>
		</bndbox>
	</object>
</annotation>
