<annotation>
	<folder>JPEGImages</folder>
	<filename>4 (13).jpg</filename>
	<path>C:\Users\赵文龙\Desktop\VOC2007\JPEGImages\4 (13).jpg</path>
	<source>
		<database>Unknown</database>
	</source>
	<size>
		<width>2730</width>
		<height>2730</height>
		<depth>3</depth>
	</size>
	<segmented>0</segmented>
	<object>
		<name>Wheat Loose Smut</name>
		<pose>Unspecified</pose>
		<truncated>0</truncated>
		<difficult>0</difficult>
		<bndbox>
			<xmin>2042</xmin>
			<ymin>1070</ymin>
			<xmax>2418</xmax>
			<ymax>1876</ymax>
		</bndbox>
	</object>
</annotation>
