<annotation>
	<folder>JPEGImages</folder>
	<filename>4 (370).jpg</filename>
	<path>C:\Users\赵文龙\Desktop\VOC2007\JPEGImages\4 (370).jpg</path>
	<source>
		<database>Unknown</database>
	</source>
	<size>
		<width>3840</width>
		<height>1958</height>
		<depth>3</depth>
	</size>
	<segmented>0</segmented>
	<object>
		<name>Wheat scab</name>
		<pose>Unspecified</pose>
		<truncated>0</truncated>
		<difficult>0</difficult>
		<bndbox>
			<xmin>2074</xmin>
			<ymin>461</ymin>
			<xmax>2372</xmax>
			<ymax>1189</ymax>
		</bndbox>
	</object>
	<object>
		<name>Wheat scab</name>
		<pose>Unspecified</pose>
		<truncated>0</truncated>
		<difficult>0</difficult>
		<bndbox>
			<xmin>2931</xmin>
			<ymin>97</ymin>
			<xmax>3569</xmax>
			<ymax>1943</ymax>
		</bndbox>
	</object>
	<object>
		<name>Wheat scab</name>
		<pose>Unspecified</pose>
		<truncated>0</truncated>
		<difficult>0</difficult>
		<bndbox>
			<xmin>423</xmin>
			<ymin>486</ymin>
			<xmax>941</xmax>
			<ymax>1202</ymax>
		</bndbox>
	</object>
</annotation>
