<annotation>
	<folder>JPEGImages</folder>
	<filename>5 (264).jpg</filename>
	<path>C:\Users\赵文龙\Desktop\VOC2007\JPEGImages\5 (264).jpg</path>
	<source>
		<database>Unknown</database>
	</source>
	<size>
		<width>2000</width>
		<height>2000</height>
		<depth>3</depth>
	</size>
	<segmented>0</segmented>
	<object>
		<name>Wheat Red Spider</name>
		<pose>Unspecified</pose>
		<truncated>0</truncated>
		<difficult>0</difficult>
		<bndbox>
			<xmin>255</xmin>
			<ymin>219</ymin>
			<xmax>711</xmax>
			<ymax>715</ymax>
		</bndbox>
	</object>
	<object>
		<name>Wheat Red Spider</name>
		<pose>Unspecified</pose>
		<truncated>0</truncated>
		<difficult>0</difficult>
		<bndbox>
			<xmin>190</xmin>
			<ymin>1093</ymin>
			<xmax>427</xmax>
			<ymax>1300</ymax>
		</bndbox>
	</object>
	<object>
		<name>Wheat Red Spider</name>
		<pose>Unspecified</pose>
		<truncated>0</truncated>
		<difficult>0</difficult>
		<bndbox>
			<xmin>570</xmin>
			<ymin>1628</ymin>
			<xmax>829</xmax>
			<ymax>1843</ymax>
		</bndbox>
	</object>
	<object>
		<name>Wheat Red Spider</name>
		<pose>Unspecified</pose>
		<truncated>0</truncated>
		<difficult>0</difficult>
		<bndbox>
			<xmin>1122</xmin>
			<ymin>1282</ymin>
			<xmax>1281</xmax>
			<ymax>1495</ymax>
		</bndbox>
	</object>
</annotation>
