<annotation>
	<folder>JPEGImages</folder>
	<filename>5 (93).jpg</filename>
	<path>C:\Users\赵文龙\Desktop\VOC2007\JPEGImages\5 (93).jpg</path>
	<source>
		<database>Unknown</database>
	</source>
	<size>
		<width>2156</width>
		<height>2160</height>
		<depth>3</depth>
	</size>
	<segmented>0</segmented>
	<object>
		<name>Wheat Red Spider</name>
		<pose>Unspecified</pose>
		<truncated>0</truncated>
		<difficult>0</difficult>
		<bndbox>
			<xmin>391</xmin>
			<ymin>198</ymin>
			<xmax>905</xmax>
			<ymax>538</ymax>
		</bndbox>
	</object>
	<object>
		<name>Wheat Red Spider</name>
		<pose>Unspecified</pose>
		<truncated>0</truncated>
		<difficult>0</difficult>
		<bndbox>
			<xmin>1268</xmin>
			<ymin>1396</ymin>
			<xmax>1681</xmax>
			<ymax>1824</ymax>
		</bndbox>
	</object>
</annotation>
