<annotation>
	<folder>JPEGImages</folder>
	<filename>1 (188).jpg</filename>
	<path>C:\Users\赵文龙\Desktop\VOC2007\JPEGImages\1 (188).jpg</path>
	<source>
		<database>Unknown</database>
	</source>
	<size>
		<width>568</width>
		<height>473</height>
		<depth>3</depth>
	</size>
	<segmented>0</segmented>
	<object>
		<name>Healthy Wheat</name>
		<pose>Unspecified</pose>
		<truncated>0</truncated>
		<difficult>0</difficult>
		<bndbox>
			<xmin>258</xmin>
			<ymin>157</ymin>
			<xmax>317</xmax>
			<ymax>343</ymax>
		</bndbox>
	</object>
	<object>
		<name>Healthy Wheat</name>
		<pose>Unspecified</pose>
		<truncated>0</truncated>
		<difficult>0</difficult>
		<bndbox>
			<xmin>393</xmin>
			<ymin>324</ymin>
			<xmax>467</xmax>
			<ymax>471</ymax>
		</bndbox>
	</object>
</annotation>
