<annotation>
	<folder>JPEGImages</folder>
	<filename>1 (270).jpg</filename>
	<path>C:\Users\赵文龙\Desktop\VOC2007\JPEGImages\1 (270).jpg</path>
	<source>
		<database>Unknown</database>
	</source>
	<size>
		<width>1375</width>
		<height>2160</height>
		<depth>1</depth>
	</size>
	<segmented>0</segmented>
	<object>
		<name>Healthy Wheat</name>
		<pose>Unspecified</pose>
		<truncated>0</truncated>
		<difficult>0</difficult>
		<bndbox>
			<xmin>274</xmin>
			<ymin>487</ymin>
			<xmax>1060</xmax>
			<ymax>1782</ymax>
		</bndbox>
	</object>
</annotation>
