<annotation>
	<folder>JPEGImages</folder>
	<filename>1 (494).jpg</filename>
	<path>C:\Users\赵文龙\Desktop\VOC2007\JPEGImages\1 (494).jpg</path>
	<source>
		<database>Unknown</database>
	</source>
	<size>
		<width>2254</width>
		<height>2160</height>
		<depth>3</depth>
	</size>
	<segmented>0</segmented>
	<object>
		<name>Healthy Wheat</name>
		<pose>Unspecified</pose>
		<truncated>0</truncated>
		<difficult>0</difficult>
		<bndbox>
			<xmin>1586</xmin>
			<ymin>122</ymin>
			<xmax>2142</xmax>
			<ymax>1101</ymax>
		</bndbox>
	</object>
	<object>
		<name>Healthy Wheat</name>
		<pose>Unspecified</pose>
		<truncated>0</truncated>
		<difficult>0</difficult>
		<bndbox>
			<xmin>979</xmin>
			<ymin>517</ymin>
			<xmax>1356</xmax>
			<ymax>1287</ymax>
		</bndbox>
	</object>
	<object>
		<name>Healthy Wheat</name>
		<pose>Unspecified</pose>
		<truncated>0</truncated>
		<difficult>0</difficult>
		<bndbox>
			<xmin>198</xmin>
			<ymin>182</ymin>
			<xmax>617</xmax>
			<ymax>1329</ymax>
		</bndbox>
	</object>
</annotation>
