<annotation>
	<folder>JPEGImages</folder>
	<filename>1 (490).jpg</filename>
	<path>C:\Users\赵文龙\Desktop\VOC2007\JPEGImages\1 (490).jpg</path>
	<source>
		<database>Unknown</database>
	</source>
	<size>
		<width>1572</width>
		<height>2160</height>
		<depth>3</depth>
	</size>
	<segmented>0</segmented>
	<object>
		<name>Healthy Wheat</name>
		<pose>Unspecified</pose>
		<truncated>0</truncated>
		<difficult>0</difficult>
		<bndbox>
			<xmin>59</xmin>
			<ymin>47</ymin>
			<xmax>443</xmax>
			<ymax>1184</ymax>
		</bndbox>
	</object>
	<object>
		<name>Healthy Wheat</name>
		<pose>Unspecified</pose>
		<truncated>0</truncated>
		<difficult>0</difficult>
		<bndbox>
			<xmin>769</xmin>
			<ymin>882</ymin>
			<xmax>1034</xmax>
			<ymax>1966</ymax>
		</bndbox>
	</object>
	<object>
		<name>Healthy Wheat</name>
		<pose>Unspecified</pose>
		<truncated>0</truncated>
		<difficult>0</difficult>
		<bndbox>
			<xmin>1110</xmin>
			<ymin>1184</ymin>
			<xmax>1357</xmax>
			<ymax>2019</ymax>
		</bndbox>
	</object>
	<object>
		<name>Healthy Wheat</name>
		<pose>Unspecified</pose>
		<truncated>1</truncated>
		<difficult>0</difficult>
		<bndbox>
			<xmin>1366</xmin>
			<ymin>1052</ymin>
			<xmax>1572</xmax>
			<ymax>1729</ymax>
		</bndbox>
	</object>
</annotation>
