<annotation>
	<folder>JPEGImages</folder>
	<filename>1 (478).jpg</filename>
	<path>C:\Users\赵文龙\Desktop\VOC2007\JPEGImages\1 (478).jpg</path>
	<source>
		<database>Unknown</database>
	</source>
	<size>
		<width>594</width>
		<height>2160</height>
		<depth>3</depth>
	</size>
	<segmented>0</segmented>
	<object>
		<name>Healthy Wheat</name>
		<pose>Unspecified</pose>
		<truncated>1</truncated>
		<difficult>0</difficult>
		<bndbox>
			<xmin>59</xmin>
			<ymin>84</ymin>
			<xmax>594</xmax>
			<ymax>1910</ymax>
		</bndbox>
	</object>
</annotation>
