<annotation>
	<folder>JPEGImages</folder>
	<filename>1 (641).jpg</filename>
	<path>C:\Users\赵文龙\Desktop\VOC2007\JPEGImages\1 (641).jpg</path>
	<source>
		<database>Unknown</database>
	</source>
	<size>
		<width>3840</width>
		<height>2005</height>
		<depth>3</depth>
	</size>
	<segmented>0</segmented>
	<object>
		<name>Healthy Wheat</name>
		<pose>Unspecified</pose>
		<truncated>1</truncated>
		<difficult>0</difficult>
		<bndbox>
			<xmin>785</xmin>
			<ymin>1</ymin>
			<xmax>1208</xmax>
			<ymax>1150</ymax>
		</bndbox>
	</object>
	<object>
		<name>Healthy Wheat</name>
		<pose>Unspecified</pose>
		<truncated>0</truncated>
		<difficult>0</difficult>
		<bndbox>
			<xmin>1446</xmin>
			<ymin>32</ymin>
			<xmax>2146</xmax>
			<ymax>1263</ymax>
		</bndbox>
	</object>
	<object>
		<name>Healthy Wheat</name>
		<pose>Unspecified</pose>
		<truncated>0</truncated>
		<difficult>0</difficult>
		<bndbox>
			<xmin>2175</xmin>
			<ymin>53</ymin>
			<xmax>2475</xmax>
			<ymax>1397</ymax>
		</bndbox>
	</object>
</annotation>
