<annotation>
	<folder>JPEGImages</folder>
	<filename>1 (718).jpg</filename>
	<path>C:\Users\赵文龙\Desktop\VOC2007\JPEGImages\1 (718).jpg</path>
	<source>
		<database>Unknown</database>
	</source>
	<size>
		<width>2259</width>
		<height>2160</height>
		<depth>3</depth>
	</size>
	<segmented>0</segmented>
	<object>
		<name>Healthy Wheat</name>
		<pose>Unspecified</pose>
		<truncated>0</truncated>
		<difficult>0</difficult>
		<bndbox>
			<xmin>651</xmin>
			<ymin>819</ymin>
			<xmax>1184</xmax>
			<ymax>1961</ymax>
		</bndbox>
	</object>
	<object>
		<name>Healthy Wheat</name>
		<pose>Unspecified</pose>
		<truncated>0</truncated>
		<difficult>0</difficult>
		<bndbox>
			<xmin>44</xmin>
			<ymin>322</ymin>
			<xmax>314</xmax>
			<ymax>1366</ymax>
		</bndbox>
	</object>
</annotation>
