<annotation>
	<folder>JPEGImages</folder>
	<filename>1 (83).jpg</filename>
	<path>C:\Users\赵文龙\Desktop\VOC2007\JPEGImages\1 (83).jpg</path>
	<source>
		<database>Unknown</database>
	</source>
	<size>
		<width>343</width>
		<height>796</height>
		<depth>3</depth>
	</size>
	<segmented>0</segmented>
	<object>
		<name>Healthy Wheat</name>
		<pose>Unspecified</pose>
		<truncated>0</truncated>
		<difficult>0</difficult>
		<bndbox>
			<xmin>42</xmin>
			<ymin>177</ymin>
			<xmax>303</xmax>
			<ymax>709</ymax>
		</bndbox>
	</object>
</annotation>
