<annotation>
	<folder>JPEGImages</folder>
	<filename>1 (907).jpg</filename>
	<path>C:\Users\赵文龙\Desktop\VOC2007\JPEGImages\1 (907).jpg</path>
	<source>
		<database>Unknown</database>
	</source>
	<size>
		<width>2647</width>
		<height>2160</height>
		<depth>3</depth>
	</size>
	<segmented>0</segmented>
	<object>
		<name>Healthy Wheat</name>
		<pose>Unspecified</pose>
		<truncated>0</truncated>
		<difficult>0</difficult>
		<bndbox>
			<xmin>331</xmin>
			<ymin>1281</ymin>
			<xmax>571</xmax>
			<ymax>2122</ymax>
		</bndbox>
	</object>
	<object>
		<name>Healthy Wheat</name>
		<pose>Unspecified</pose>
		<truncated>0</truncated>
		<difficult>0</difficult>
		<bndbox>
			<xmin>1840</xmin>
			<ymin>905</ymin>
			<xmax>2033</xmax>
			<ymax>1612</ymax>
		</bndbox>
	</object>
</annotation>
